modbus_wrapper/__init__.py
modbus_wrapper/client.py
modbus_wrapper/function_argument.py
modbus_wrapper/modbus_function_code.py
modbus_wrapper/object_factory.py
modbus_wrapper/objects/__init__.py
modbus_wrapper/objects/config.py
modbus_wrapper/objects/fatek_object.py
modbus_wrapper/objects/modbus_object.py
modbus_wrapper/objects/modbus_value.py
modbus_wrapper-1.0.2.dist-info/METADATA
modbus_wrapper-1.0.2.dist-info/WHEEL
modbus_wrapper-1.0.2.dist-info/top_level.txt
modbus_wrapper-1.0.2.dist-info/RECORD
