Metadata-Version: 2.1
Name: modbus-wrapper
Version: 1.0.2
Summary: wrapper for pyModbusTCP accepting all Modbus numbers with Fatek support
Home-page: https://github.com/pbubas/modbus_wrapper
Author: Przemyslaw Bubas
Author-email: bubasenator@gmail.com
Keywords: modbus fatek
Requires-Dist: pyModbusTCP
